Linear/DoublyCLL.py
Linear/DoublyLL.py
Linear/LLQueue.py
Linear/LLStack.py
Linear/SinglyCLL.py
Linear/SinglyLL.py
Linear/__init__.py
Nodes/DoublyNode.py
Nodes/SinglyNode.py
Nodes/TNode.py
Nodes/__init__.py
Trees/AVL.py
Trees/BST.py
Trees/__init__.py
test/AVL_test.py
test/BST_test.py
test/DoublyCLL_test.py
test/DoublyLL_test.py
test/LLQueue_test.py
test/LLStack_test.py
test/SinglyCLL_test.py
test/SinglyLL_test.py
test/__init__.py
lmah88-1.4.dist-info/METADATA
lmah88-1.4.dist-info/WHEEL
lmah88-1.4.dist-info/top_level.txt
lmah88-1.4.dist-info/RECORD
