Metadata-Version: 2.1
Name: lmah88
Version: 1.4
Summary: ENSF 338 Final Project
Author: Liam and Theodore
